row2vec/__init__.py
row2vec/api.py
row2vec/architecture_search.py
row2vec/auto_dimension.py
row2vec/categorical_encoding.py
row2vec/cli.py
row2vec/config.py
row2vec/core.py
row2vec/imputation.py
row2vec/logging.py
row2vec/pandas.py
row2vec/pipeline_builder.py
row2vec/py.typed
row2vec/serialization.py
row2vec/sklearn.py
row2vec/utils.py
row2vec-0.1.0.dist-info/licenses/LICENSE
row2vec-0.1.0.dist-info/METADATA
row2vec-0.1.0.dist-info/WHEEL
row2vec-0.1.0.dist-info/entry_points.txt
row2vec-0.1.0.dist-info/top_level.txt
row2vec-0.1.0.dist-info/RECORD
