Metadata-Version: 2.4
Name: row2vec
Version: 0.1.0
Summary: A Python library for easily generating low-dimensional vector embeddings from any tabular dataset.
Author-email: Tiago Tresoldi <tiago@tresoldi.org>
Maintainer-email: Tiago Tresoldi <tiago@tresoldi.org>
License-Expression: MIT
Project-URL: Homepage, https://github.com/evotext/row2vec
Project-URL: Repository, https://github.com/evotext/row2vec
Project-URL: Documentation, https://github.com/evotext/row2vec#readme
Project-URL: Issues, https://github.com/evotext/row2vec/issues
Project-URL: Changelog, https://github.com/evotext/row2vec/blob/main/CHANGELOG.md
Keywords: embeddings,machine-learning,deep-learning,dimensionality-reduction,autoencoder,tabular-data,representation-learning,tensorflow,keras,pca,tsne,umap
Classifier: Development Status :: 4 - Beta
Classifier: Intended Audience :: Developers
Classifier: Intended Audience :: Science/Research
Classifier: Operating System :: OS Independent
Classifier: Programming Language :: Python :: 3
Classifier: Programming Language :: Python :: 3.10
Classifier: Programming Language :: Python :: 3.11
Classifier: Programming Language :: Python :: 3.12
Classifier: Topic :: Scientific/Engineering :: Artificial Intelligence
Classifier: Topic :: Software Development :: Libraries :: Python Modules
Classifier: Typing :: Typed
Requires-Python: >=3.10
License-File: LICENSE
Requires-Dist: numpy>=1.21.0
Requires-Dist: pandas>=1.5.3
Requires-Dist: scikit-learn>=1.0.0
Requires-Dist: tensorflow>=2.8.0
Requires-Dist: jinja2>=3.1.2
Requires-Dist: psutil>=5.8.0
Requires-Dist: umap-learn>=0.5.0
Requires-Dist: click>=8.0.0
Requires-Dist: rich>=12.0.0
Requires-Dist: pyyaml>=6.0.0
Provides-Extra: dev
Requires-Dist: pytest>=7.0.0; extra == "dev"
Requires-Dist: pytest-cov>=4.0.0; extra == "dev"
Requires-Dist: pytest-mock>=3.10.0; extra == "dev"
Requires-Dist: pytest-xdist>=3.0.0; extra == "dev"
Requires-Dist: mypy>=1.0.0; extra == "dev"
Requires-Dist: ruff>=0.1.0; extra == "dev"
Requires-Dist: types-psutil; extra == "dev"
Requires-Dist: types-PyYAML>=6.0.0; extra == "dev"
Requires-Dist: pandas-stubs>=2.0.0; extra == "dev"
Requires-Dist: build>=0.10.0; extra == "dev"
Requires-Dist: twine>=4.0.0; extra == "dev"
Requires-Dist: nhandu>=0.1.0; extra == "dev"
Provides-Extra: docs
Requires-Dist: sphinx>=5.0.0; extra == "docs"
Requires-Dist: sphinx-rtd-theme>=1.0.0; extra == "docs"
Requires-Dist: myst-parser>=0.18.0; extra == "docs"
Provides-Extra: test
Requires-Dist: pytest>=7.0.0; extra == "test"
Requires-Dist: pytest-cov>=4.0.0; extra == "test"
Requires-Dist: pytest-mock>=3.10.0; extra == "test"
Dynamic: license-file
